{
  "$schema": "https://developer.microsoft.com/json-schemas/fabric/item/report/definition/visualContainer/2.5.0/schema.json",
  "name": "2346adf08a2fd076307c",
  "position": {
    "x": 18.480243161094226,
    "y": 661.39817629179333,
    "z": 13000,
    "height": 35.987841945288757,
    "width": 70.030395136778125,
    "tabOrder": 13000
  },
  "visual": {
    "visualType": "actionButton",
    "objects": {
      "icon": [
        {
          "properties": {
            "shapeType": {
              "expr": {
                "Literal": {
                  "Value": "'rightArrow'"
                }
              }
            },
            "lineColor": {
              "solid": {
                "color": {
                  "expr": {
                    "ThemeDataColor": {
                      "ColorId": 1,
                      "Percent": 0
                    }
                  }
                }
              }
            },
            "horizontalAlignment": {
              "expr": {
                "Literal": {
                  "Value": "'center'"
                }
              }
            }
          },
          "selector": {
            "id": "default"
          }
        },
        {
          "properties": {
            "show": {
              "expr": {
                "Literal": {
                  "Value": "true"
                }
              }
            }
          }
        }
      ],
      "text": [
        {
          "properties": {
            "show": {
              "expr": {
                "Literal": {
                  "Value": "false"
                }
              }
            }
          }
        }
      ]
    },
    "visualContainerObjects": {
      "visualLink": [
        {
          "properties": {
            "show": {
              "expr": {
                "Literal": {
                  "Value": "true"
                }
              }
            },
            "type": {
              "expr": {
                "Literal": {
                  "Value": "'PageNavigation'"
                }
              }
            },
            "navigationSection": {
              "expr": {
                "Literal": {
                  "Value": "'a689eae0ac8013f8de93'"
                }
              }
            }
          }
        }
      ]
    },
    "drillFilterOtherVisuals": true
  },
  "howCreated": "InsertVisualButton"
}